pee/__init__.py
pee/pee.py
pee-0.1.1.dist-info/LICENSE
pee-0.1.1.dist-info/METADATA
pee-0.1.1.dist-info/WHEEL
pee-0.1.1.dist-info/entry_points.txt
pee-0.1.1.dist-info/top_level.txt
pee-0.1.1.dist-info/RECORD
