Metadata-Version: 2.1
Name: pee
Version: 0.1.1
Summary: Display memory system information
Home-page: https://github.com/breakthatbass/pee
Author: Taylor Gamache
Author-email: gamache.taylor@gmail.com
License: MIT
Platform: UNKNOWN
Requires-Python: >=3.6
